drlx/__init__.py
drlx/configs.py
drlx/denoisers/__init__.py
drlx/denoisers/ldm_unet.py
drlx/pipeline/__init__.py
drlx/pipeline/imagenet_animal_prompts.py
drlx/pipeline/pickapic_prompts.py
drlx/reward_modelling/__init__.py
drlx/reward_modelling/aesthetics.py
drlx/reward_modelling/pickscore.py
drlx/reward_modelling/toy_rewards.py
drlx/sampling/__init__.py
drlx/trainer/__init__.py
drlx/trainer/ddpo_trainer.py
drlx/trainer/ldm_trainer.py
drlx/utils/__init__.py
drlx-0.0.2.dist-info/METADATA
drlx-0.0.2.dist-info/WHEEL
drlx-0.0.2.dist-info/top_level.txt
drlx-0.0.2.dist-info/RECORD
