Metadata-Version: 2.1
Name: drlx
Version: 0.0.2
Summary: DRLX is a library for distributed training of diffusion models via RL
Author: CarperAI
License: MIT
Classifier: Development Status :: 3 - Alpha
Classifier: Environment :: Console
Classifier: Intended Audience :: Science/Research
Classifier: Intended Audience :: Developers
Classifier: License :: OSI Approved :: MIT License
Classifier: Natural Language :: English
Classifier: Programming Language :: Python
Classifier: Programming Language :: Python :: 3
Classifier: Programming Language :: Python :: 3.9
Classifier: Programming Language :: Python :: 3.10
Classifier: Programming Language :: Python :: 3 :: Only
Classifier: Programming Language :: Python :: Implementation :: CPython
Classifier: Topic :: Scientific/Engineering :: Artificial Intelligence
Classifier: Typing :: Typed
Classifier: Operating System :: Unix
Requires-Python: >=3.9
Requires-Dist: torch
Requires-Dist: torchvision
Requires-Dist: torchtyping
Requires-Dist: einops
Requires-Dist: diffusers
Requires-Dist: transformers
Requires-Dist: accelerate
Requires-Dist: xformers
Requires-Dist: wandb
Requires-Dist: fastprogress
Requires-Dist: matplotlib
Provides-Extra: benchmarks
Requires-Dist: pygraphviz ; extra == 'benchmarks'
Requires-Dist: graphviz ; extra == 'benchmarks'
Requires-Dist: openai ; extra == 'benchmarks'
Provides-Extra: dev
Requires-Dist: black ; extra == 'dev'
Requires-Dist: isort ; extra == 'dev'
Requires-Dist: flake8 ; extra == 'dev'
Requires-Dist: flake8-pyproject ; extra == 'dev'
Requires-Dist: pydocstyle ; extra == 'dev'
Requires-Dist: mypy ; extra == 'dev'
Requires-Dist: pre-commit ; extra == 'dev'
Requires-Dist: pytest ; extra == 'dev'
Requires-Dist: pytest-cov ; extra == 'dev'
Provides-Extra: docs
Requires-Dist: sphinx ==5.3.0 ; extra == 'docs'
Requires-Dist: sphinx-rtd-theme ; extra == 'docs'
Requires-Dist: sphinx-autodoc-typehints ; extra == 'docs'
Provides-Extra: notebook
Requires-Dist: ipython ; extra == 'notebook'
Provides-Extra: sodaracer
Requires-Dist: swig >=4.1.0 ; extra == 'sodaracer'
Requires-Dist: box2d-py ==2.3.8 ; extra == 'sodaracer'
Requires-Dist: pygame ; extra == 'sodaracer'
Provides-Extra: triton
Requires-Dist: tritonclient[all] ; extra == 'triton'
